{
  "schemaVersion": 1,
  "node": "s4e.notebook",
  "inputs": [
    {
      "path": "brief.md",
      "sha256": "6e440a2fea779cc7d933d83b6e5fff5947abd8e86e3e0dbf91d4b1e60de5b295"
    },
    {
      "path": "storyboard.yaml",
      "sha256": "bcda24eb4bb5f0b04ea436e6f9769e86f816e241310d3f23c79ab0bbef4701b3"
    },
    {
      "path": "doc/lesson.md",
      "sha256": "c9e3438d65555d1051da9b23cc68926a98ad615d77beb4a737971827554bb554"
    }
  ],
  "outputs": [
    {
      "path": "notebook/lesson.ipynb",
      "sha256": "fad2b82583e85b41670360117fb055c80e109d2e855bf2388bda9da2079c43f7"
    }
  ],
  "gate": {
    "passed": true,
    "checks": [
      {
        "id": "nb.json",
        "pass": true
      },
      {
        "id": "nb.numpy-only",
        "pass": true
      },
      {
        "id": "nb.executes",
        "pass": true
      }
    ]
  },
  "iterations": 1,
  "costUsd": 0.3464226,
  "tier": "sonnet",
  "startedAt": "2026-07-05T07:10:08.268Z",
  "endedAt": "2026-07-05T07:12:09.521Z",
  "transcript": "",
  "promptSha": "",
  "meta": {
    "attempts": 1,
    "executor": "checks/run_notebook.py (stdlib exec runner; no jupyter on this machine)"
  }
}
